README.md
setup.cfg
setup.py
python_loc_counter/LOCCounter.py
python_loc_counter/__init__.py
python_loc_counter.egg-info/PKG-INFO
python_loc_counter.egg-info/SOURCES.txt
python_loc_counter.egg-info/dependency_links.txt
python_loc_counter.egg-info/top_level.txt