Metadata-Version: 2.1
Name: python-loc-counter
Version: 0.2
Summary: Get LOC metrics for python scripts
Home-page: https://github.com/BryceV/python_loc_counter
Author: Bryce Vonilten
Author-email: ki6bpd@gmail.com
License: MIT
Download-URL: https://github.com/BryceV/python_loc_counter/archive/v.02.tar.gz
Keywords: python,lines of code,loc
Platform: UNKNOWN
Classifier: Development Status :: 3 - Alpha
Classifier: Intended Audience :: Developers
Classifier: Topic :: Software Development :: Build Tools
Classifier: License :: OSI Approved :: MIT License
Classifier: Programming Language :: Python :: 3.7
